sec_parsers/__init__.py
sec_parsers/cleaning.py
sec_parsers/css_detectors.py
sec_parsers/detectors.py
sec_parsers/download.py
sec_parsers/element_detector_groups.py
sec_parsers/filing.py
sec_parsers/parsers.py
sec_parsers/parsers_helper.py
sec_parsers/string_detector_groups.py
sec_parsers/string_detectors.py
sec_parsers/style_detection.py
sec_parsers/tag_detectors.py
sec_parsers/visualization_helper.py
sec_parsers/xml_helper.py
sec_parsers-0.549.dist-info/METADATA
sec_parsers-0.549.dist-info/WHEEL
sec_parsers-0.549.dist-info/top_level.txt
sec_parsers-0.549.dist-info/RECORD
