Metadata-Version: 2.1
Name: sec-parsers
Version: 0.549
Summary: A package to parse SEC filings
Home-page: https://github.com/john-friedman/SEC-Parsers
Author: John Friedman
Requires-Dist: lxml
Requires-Dist: requests
Provides-Extra: all
Requires-Dist: sec-downloaders ; extra == 'all'
Requires-Dist: sec-visualizers ; extra == 'all'
Provides-Extra: downloaders
Requires-Dist: sec-downloaders ; extra == 'downloaders'
Provides-Extra: visualizers
Requires-Dist: sec-visualizers ; extra == 'visualizers'
